pec_trainer/__init__.py
pec_trainer/__main__.py
pec_trainer/pec_telescope.py
pec_trainer/pec_trainer_main.py
pectrainer-1.0.0.dist-info/LICENSE
pectrainer-1.0.0.dist-info/METADATA
pectrainer-1.0.0.dist-info/WHEEL
pectrainer-1.0.0.dist-info/entry_points.txt
pectrainer-1.0.0.dist-info/top_level.txt
pectrainer-1.0.0.dist-info/RECORD
