Metadata-Version: 2.1
Name: pectrainer
Version: 1.0.0
Summary: Train PEC for Celestron mounts
Author-email: Frank Freestar8n <freestar8n@yahoo.com>
License: MIT License
Project-URL: Homepage, https://github.com/freestar8n/PECTrainer
Keywords: pec,celestron,autoguide
Classifier: License :: OSI Approved :: MIT License
Classifier: Programming Language :: Python
Classifier: Programming Language :: Python :: 3
Requires-Python: >=3.7
License-File: LICENSE
Requires-Dist: numpy (>=1.24)
Requires-Dist: pywin32 (>=304)
Requires-Dist: wxmplot (>=0.9.53)
